nose2unitth/VERSION
nose2unitth/__init__.py
nose2unitth/__main__.py
nose2unitth/core.py
nose2unitth-0.0.13.dist-info/METADATA
nose2unitth-0.0.13.dist-info/RECORD
nose2unitth-0.0.13.dist-info/WHEEL
nose2unitth-0.0.13.dist-info/entry_points.txt
nose2unitth-0.0.13.dist-info/top_level.txt
