Metadata-Version: 2.1
Name: nose2unitth
Version: 0.0.13
Summary: Convert nose-style test reports to UnitTH-style test reports
Home-page: https://github.com/KarrLab/nose2unitth
Author: Jonathan Karr
Author-email: jonrkarr@gmail.com
License: MIT
Download-URL: https://github.com/KarrLab/nose2unitth
Keywords: nose unitth xunit junit
Platform: UNKNOWN
Classifier: Development Status :: 3 - Alpha
Classifier: Intended Audience :: Developers
Classifier: Topic :: Software Development :: Build Tools
Classifier: License :: OSI Approved :: MIT License
Classifier: Programming Language :: Python
Provides-Extra: tests
Provides-Extra: docs
Provides-Extra: all
Requires-Dist: cement (>=3.0.0)
Requires-Dist: setuptools
Provides-Extra: all
Requires-Dist: mock; extra == 'all'
Requires-Dist: sphinx (>=1.8); extra == 'all'
Requires-Dist: sphinx-rtd-theme (>=0.4.2); extra == 'all'
Requires-Dist: sphinxcontrib-addmetahtml (>=0.1.1); extra == 'all'
Requires-Dist: sphinxcontrib-bibtex; extra == 'all'
Requires-Dist: sphinxcontrib-googleanalytics (>=0.1.1); extra == 'all'
Requires-Dist: sphinxcontrib-spelling; extra == 'all'
Requires-Dist: sphinxprettysearchresults; extra == 'all'
Provides-Extra: docs
Requires-Dist: sphinx (>=1.8); extra == 'docs'
Requires-Dist: sphinx-rtd-theme (>=0.4.2); extra == 'docs'
Requires-Dist: sphinxcontrib-addmetahtml (>=0.1.1); extra == 'docs'
Requires-Dist: sphinxcontrib-bibtex; extra == 'docs'
Requires-Dist: sphinxcontrib-googleanalytics (>=0.1.1); extra == 'docs'
Requires-Dist: sphinxcontrib-spelling; extra == 'docs'
Requires-Dist: sphinxprettysearchresults; extra == 'docs'
Provides-Extra: tests
Requires-Dist: mock; extra == 'tests'
